pytesira/__init__.py
pytesira/dsp.py
pytesira/block/AudioOutput.py
pytesira/block/DanteInput.py
pytesira/block/DanteOutput.py
pytesira/block/Ducker.py
pytesira/block/GraphicEqualizer.py
pytesira/block/LevelControl.py
pytesira/block/MuteControl.py
pytesira/block/NoiseGenerator.py
pytesira/block/PassFilter.py
pytesira/block/SourceSelector.py
pytesira/block/UsbInput.py
pytesira/block/UsbOutput.py
pytesira/block/base_dante.py
pytesira/block/base_level_mute.py
pytesira/block/base_level_mute_no_subscription.py
pytesira/block/base_usb.py
pytesira/block/block.py
pytesira/transport/ssh.py
pytesira/transport/transport.py
pytesira/util/band.py
pytesira/util/channel.py
pytesira/util/indexed_object.py
pytesira/util/indexed_object_with_level.py
pytesira/util/source.py
pytesira/util/ttp_response.py
pytesira/util/types.py
pytesira-0.9.0.dist-info/METADATA
pytesira-0.9.0.dist-info/WHEEL
pytesira-0.9.0.dist-info/licenses/LICENSE.md
pytesira-0.9.0.dist-info/RECORD
