Metadata-Version: 2.4
Name: pytesira
Version: 0.9.0
Summary: Control your Biamp Tesira DSPs directly from Python!
Project-URL: Homepage, https://github.com/enp6s0/pytesira
Project-URL: Repository, https://github.com/enp6s0/pytesira.git
Project-URL: Issues, https://github.com/enp6s0/pytesira/issues
Author: @enp6s0
License-Expression: MIT
License-File: LICENSE.md
Classifier: Development Status :: 4 - Beta
Classifier: Intended Audience :: Developers
Classifier: Programming Language :: Python :: 3.10
Classifier: Programming Language :: Python :: 3.11
Classifier: Programming Language :: Python :: 3.12
Classifier: Programming Language :: Python :: 3.13
Requires-Python: >=3.10
Requires-Dist: paramiko>=3.5.0
Requires-Dist: pytest>=7.4.0
Provides-Extra: dev
Requires-Dist: black>=25.1.0; extra == 'dev'
Requires-Dist: flake8>=6.0.0; extra == 'dev'
